{
  "id": "user-sipgb",
  "name": "Sipgb",
  "currency": 17000,
  "players": [
    {
      "id": "Torte-5227-0818",
      "purchasedAt": 1760389692005
    },
    {
      "id": "Togore-Dreemurr-6731-0027",
      "purchasedAt": 1760389741574
    },
    {
      "id": "Cozmic-6706-5616",
      "purchasedAt": 1760389766469
    },
    {
      "id": "AxelTS-7913-9686",
      "purchasedAt": 1760389830320
    },
    {
      "id": "YamineLamal-4171-9482",
      "purchasedAt": 1760448255362
    },
    {
      "id": "Akusika-5146-4024",
      "purchasedAt": 1760448262546
    }
  ],
  "roster": {
    "lineup": [
      "Torte-5227-0818",
      "Togore-Dreemurr-6731-0027",
      "Cozmic-6706-5616",
      "AxelTS-7913-9686",
      "Akusika-5146-4024",
      "YamineLamal-4171-9482"
    ],
    "bench": []
  },
  "weeklyScores": {},
  "bids": {
    "Pein36-5539-7293": 5991
  }
}