[
  {
    "id": "yosh.-4808-9390",
    "name": "yosh.",
    "icon": "Luigi",
    "cost": 4823,
    "stats": {
      "speed": 2,
      "acceleration": 9,
      "weight": 4,
      "handling": 9,
      "traction": 5
    },
    "mmr": 5366,
    "peak_mmr": 4808,
    "rank": 2779,
    "events_played": 10,
    "country": "United States",
    "game_stats": {
      "1v1": {
        "events_played": 10,
        "win_rate": "50.0%",
        "win_loss_last_10": "5 - 5",
        "gainloss_last_10": -199,
        "largest_gain": 193,
        "average_score": 82.9,
        "average_score_no_sq": 82.9,
        "average_score_last_10": 82.9,
        "partner_average_score": 76.6,
        "partner_average_score_no_sq": 76.6
      },
      "2v2": {}
    },
    "registry_url": "https://mkcentral.com/registry/players/profile?id=12020"
  },
  {
    "id": "KnDo-5606-5206",
    "name": "KnDo",
    "icon": "Peach",
    "cost": 5958,
    "stats": {
      "speed": 8,
      "acceleration": 8,
      "weight": 2,
      "handling": 6,
      "traction": 8
    },
    "mmr": 4852,
    "peak_mmr": 5606,
    "rank": 2406,
    "events_played": 64,
    "country": "United Kingdom",
    "game_stats": {
      "1v1": {
        "events_played": 57,
        "win_rate": "52.6%",
        "win_loss_last_10": "3 - 7",
        "gainloss_last_10": -463,
        "largest_gain": 226,
        "average_score": 81.4,
        "average_score_no_sq": 81.6,
        "average_score_last_10": 75.9,
        "partner_average_score": 83.5,
        "partner_average_score_no_sq": 83.8
      },
      "2v2": {
        "events_played": 7,
        "win_rate": "57.1%",
        "win_loss_last_10": "4 - 3",
        "gainloss_last_10": 14,
        "largest_gain": 146,
        "average_score": 70.1,
        "average_score_last_10": 70.1,
        "partner_average_score": 72.9
      }
    },
    "registry_url": "https://mkcentral.com/registry/players/profile?id=69529"
  },
  {
    "id": "Kado-5507-3805",
    "name": "Kado",
    "icon": "Mario",
    "cost": 5864,
    "stats": {
      "speed": 5,
      "acceleration": 2,
      "weight": 8,
      "handling": 5,
      "traction": 4
    },
    "mmr": 5911,
    "peak_mmr": 5507,
    "rank": 1594,
    "events_played": 6,
    "country": "France",
    "game_stats": {
      "1v1": {
        "events_played": 6,
        "win_rate": "33.3%",
        "win_loss_last_10": "2 - 4",
        "gainloss_last_10": -182,
        "largest_gain": 100,
        "average_score": 74.5,
        "average_score_no_sq": 89,
        "average_score_last_10": 74.5,
        "partner_average_score": 87.1
      },
      "2v2": {}
    },
    "registry_url": "https://mkcentral.com/registry/players/profile?id=38819"
  },
  {
    "id": "Mirymeg-10402-8898",
    "name": "Mirymeg",
    "icon": "Peach",
    "cost": 10750,
    "stats": {
      "speed": 4,
      "acceleration": 8,
      "weight": 5,
      "handling": 2,
      "traction": 6
    },
    "mmr": 11498,
    "peak_mmr": 10402,
    "rank": 44,
    "events_played": 83,
    "country": "United States",
    "game_stats": {
      "1v1": {
        "events_played": 67,
        "win_rate": "53.7%",
        "win_loss_last_10": "6 - 4",
        "gainloss_last_10": 488,
        "largest_gain": 247,
        "average_score": 85.6,
        "average_score_no_sq": 85.6,
        "average_score_last_10": 84.1,
        "partner_average_score": 83.7,
        "partner_average_score_no_sq": 85.3
      },
      "2v2": {
        "events_played": 16,
        "win_rate": "50.0%",
        "win_loss_last_10": "7 - 3",
        "gainloss_last_10": 400,
        "largest_gain": 195,
        "average_score": 77.2,
        "average_score_no_sq": 76.7,
        "average_score_last_10": 80.3,
        "partner_average_score": 73.1
      }
    },
    "registry_url": "https://mkcentral.com/registry/players/profile?id=58497"
  },
  {
    "id": "Octo-5470-2438",
    "name": "Octo",
    "icon": "Bowser",
    "cost": 5350,
    "stats": {
      "speed": 8,
      "acceleration": 8,
      "weight": 7,
      "handling": 6,
      "traction": 2
    },
    "mmr": 5833,
    "peak_mmr": 5470,
    "rank": 1640,
    "events_played": 29,
    "country": "Switzerland",
    "game_stats": {
      "1v1": {
        "events_played": 29,
        "win_rate": "51.7%",
        "win_loss_last_10": "5 - 5",
        "gainloss_last_10": 302,
        "largest_gain": 207,
        "average_score": 83.8,
        "average_score_no_sq": 83.8,
        "average_score_last_10": 83.7,
        "partner_average_score": 84.2,
        "partner_average_score_no_sq": 84.2
      },
      "2v2": {}
    },
    "registry_url": "https://mkcentral.com/registry/players/profile?id=13925"
  },
  {
    "id": "Upachaya-5970-7194",
    "name": "Upachaya",
    "icon": "Toad",
    "cost": 5854,
    "stats": {
      "speed": 4,
      "acceleration": 8,
      "weight": 4,
      "handling": 2,
      "traction": 7
    },
    "mmr": 6642,
    "peak_mmr": 5970,
    "rank": 1357,
    "events_played": 50,
    "country": "United States",
    "game_stats": {
      "1v1": {
        "events_played": 49,
        "win_rate": "51.0%",
        "win_loss_last_10": "5 - 5",
        "gainloss_last_10": -37,
        "largest_gain": 220,
        "average_score": 83.3,
        "average_score_no_sq": 83.3,
        "average_score_last_10": 84.2,
        "partner_average_score": 80.3,
        "partner_average_score_no_sq": 80.8
      },
      "2v2": {
        "events_played": 1,
        "win_rate": "0.0%",
        "win_loss_last_10": "0 - 1",
        "gainloss_last_10": -90,
        "average_score": 62,
        "average_score_no_sq": 62,
        "average_score_last_10": 62
      }
    },
    "registry_url": "https://mkcentral.com/registry/players/profile?id=17346"
  },
  {
    "id": "Maq-5366-2531",
    "name": "Maq",
    "icon": "Mario",
    "cost": 5471,
    "stats": {
      "speed": 8,
      "acceleration": 9,
      "weight": 6,
      "handling": 7,
      "traction": 5
    },
    "mmr": 5514,
    "peak_mmr": 5366,
    "rank": 2379,
    "events_played": 60,
    "country": "United States",
    "game_stats": {
      "1v1": {
        "events_played": 60,
        "win_rate": "51.7%",
        "win_loss_last_10": "4 - 6",
        "gainloss_last_10": -64,
        "largest_gain": 200,
        "average_score": 83.9,
        "average_score_no_sq": 84.8,
        "average_score_last_10": 82.6,
        "partner_average_score": 81.3,
        "partner_average_score_no_sq": 81.8
      },
      "2v2": {}
    },
    "registry_url": "https://mkcentral.com/registry/players/profile?id=15192"
  },
  {
    "id": "Luckyllua-6284-9220",
    "name": "Luckyllua",
    "icon": "Toad",
    "cost": 6392,
    "stats": {
      "speed": 6,
      "acceleration": 2,
      "weight": 9,
      "handling": 6,
      "traction": 3
    },
    "mmr": 6513,
    "peak_mmr": 6284,
    "rank": 1081,
    "events_played": 15,
    "country": "France",
    "game_stats": {
      "1v1": {
        "events_played": 12,
        "win_rate": "58.3%",
        "win_loss_last_10": "5 - 5",
        "gainloss_last_10": 96,
        "largest_gain": 208,
        "average_score": 83.4,
        "average_score_no_sq": 77.6,
        "average_score_last_10": 83.7,
        "partner_average_score": 81.3,
        "partner_average_score_no_sq": 94.5
      },
      "2v2": {
        "events_played": 3,
        "win_rate": "33.3%",
        "win_loss_last_10": "1 - 2",
        "gainloss_last_10": 8,
        "largest_gain": 197,
        "average_score": 81.7,
        "average_score_last_10": 81.7,
        "partner_average_score": 65.8
      }
    },
    "registry_url": "https://mkcentral.com/registry/players/profile?id=42056"
  },
  {
    "id": "Lollenzo-6667-7215",
    "name": "Lollenzo",
    "icon": "Mario",
    "cost": 6506,
    "stats": {
      "speed": 5,
      "acceleration": 4,
      "weight": 4,
      "handling": 7,
      "traction": 5
    },
    "mmr": 5866,
    "peak_mmr": 6667,
    "rank": 803,
    "events_played": 162,
    "country": "Italy",
    "game_stats": {
      "1v1": {
        "events_played": 157,
        "win_rate": "51.0%",
        "win_loss_last_10": "5 - 5",
        "gainloss_last_10": 563,
        "largest_gain": 223,
        "average_score": 84.7,
        "average_score_no_sq": 84,
        "average_score_last_10": 89.8,
        "partner_average_score": 79.8,
        "partner_average_score_no_sq": 79.3
      },
      "2v2": {
        "events_played": 5,
        "win_rate": "20.0%",
        "win_loss_last_10": "1 - 4",
        "gainloss_last_10": -590,
        "largest_gain": 137,
        "average_score": 67.2,
        "average_score_last_10": 67.2,
        "partner_average_score": 66.6
      }
    },
    "registry_url": "https://mkcentral.com/registry/players/profile?id=69992"
  },
  {
    "id": "BlazeFR-4738-8501",
    "name": "BlazeFR",
    "icon": "Koopa",
    "cost": 5140,
    "stats": {
      "speed": 4,
      "acceleration": 6,
      "weight": 9,
      "handling": 8,
      "traction": 6
    },
    "mmr": 4540,
    "peak_mmr": 4738,
    "rank": 3220,
    "events_played": 23,
    "country": "France",
    "game_stats": {
      "1v1": {
        "events_played": 23,
        "win_rate": "52.2%",
        "win_loss_last_10": "5 - 5",
        "gainloss_last_10": -154,
        "largest_gain": 191,
        "average_score": 75.7,
        "average_score_no_sq": 75.8,
        "average_score_last_10": 72,
        "partner_average_score": 89.9,
        "partner_average_score_no_sq": 90
      },
      "2v2": {}
    },
    "registry_url": "https://mkcentral.com/registry/players/profile?id=473"
  },
  {
    "id": "Naldo-7484-9386",
    "name": "Naldo",
    "icon": "DK",
    "cost": 7764,
    "stats": {
      "speed": 6,
      "acceleration": 6,
      "weight": 3,
      "handling": 2,
      "traction": 3
    },
    "mmr": 7229,
    "peak_mmr": 7484,
    "rank": 313,
    "events_played": 57,
    "country": "Chile",
    "game_stats": {
      "1v1": {
        "events_played": 57,
        "win_rate": "52.6%",
        "win_loss_last_10": "6 - 4",
        "gainloss_last_10": 279,
        "largest_gain": 225,
        "average_score": 84.8,
        "average_score_no_sq": 83.8,
        "average_score_last_10": 84.9,
        "partner_average_score": 78.6,
        "partner_average_score_no_sq": 78.1
      },
      "2v2": {}
    },
    "registry_url": "https://mkcentral.com/registry/players/profile?id=69217"
  },
  {
    "id": "Astre-7418-2928",
    "name": "Astre",
    "icon": "Koopa",
    "cost": 7961,
    "stats": {
      "speed": 4,
      "acceleration": 3,
      "weight": 9,
      "handling": 5,
      "traction": 9
    },
    "mmr": 7061,
    "peak_mmr": 7418,
    "rank": 415,
    "events_played": 23,
    "country": "Switzerland",
    "game_stats": {
      "1v1": {
        "events_played": 23,
        "win_rate": "56.5%",
        "win_loss_last_10": "6 - 4",
        "gainloss_last_10": 527,
        "largest_gain": 227,
        "average_score": 91.7,
        "average_score_no_sq": 93.6,
        "average_score_last_10": 92.6,
        "partner_average_score": 76.4,
        "partner_average_score_no_sq": 80.3
      },
      "2v2": {}
    },
    "registry_url": "https://mkcentral.com/registry/players/profile?id=3469"
  },
  {
    "id": "Sipgb-5495-5827",
    "name": "Sipgb",
    "icon": "DK",
    "cost": 5628,
    "stats": {
      "speed": 9,
      "acceleration": 6,
      "weight": 6,
      "handling": 5,
      "traction": 2
    },
    "mmr": 4820,
    "peak_mmr": 5495,
    "rank": 1704,
    "events_played": 28,
    "country": "Sweden",
    "game_stats": {
      "1v1": {
        "events_played": 26,
        "win_rate": "46.2%",
        "win_loss_last_10": "6 - 4",
        "gainloss_last_10": 311,
        "largest_gain": 218,
        "average_score": 77.5,
        "average_score_no_sq": 85.5,
        "average_score_last_10": 82.4,
        "partner_average_score": 84.4,
        "partner_average_score_no_sq": 77.8
      },
      "2v2": {
        "events_played": 2,
        "win_rate": "50.0%",
        "win_loss_last_10": "1 - 1",
        "gainloss_last_10": -14,
        "largest_gain": 110,
        "average_score": 68.5,
        "average_score_last_10": 68.5,
        "partner_average_score": 67.5
      }
    },
    "registry_url": "https://mkcentral.com/registry/players/profile?id=68279"
  },
  {
    "id": "latoiture-6719-4188",
    "name": "latoiture",
    "icon": "Bowser",
    "cost": 7200,
    "stats": {
      "speed": 9,
      "acceleration": 2,
      "weight": 9,
      "handling": 9,
      "traction": 6
    },
    "mmr": 5789,
    "peak_mmr": 6719,
    "rank": 564,
    "events_played": 15,
    "country": "France",
    "game_stats": {
      "1v1": {
        "events_played": 15,
        "win_rate": "66.7%",
        "win_loss_last_10": "7 - 3",
        "gainloss_last_10": 374,
        "largest_gain": 206,
        "average_score": 80.6,
        "average_score_no_sq": 87,
        "average_score_last_10": 78.4,
        "partner_average_score": 84.5
      },
      "2v2": {}
    },
    "registry_url": "https://mkcentral.com/registry/players/profile?id=8307"
  },
  {
    "id": "The_mystery4321-6070-0496",
    "name": "The_mystery4321",
    "icon": "DK",
    "cost": 6131,
    "stats": {
      "speed": 8,
      "acceleration": 5,
      "weight": 7,
      "handling": 3,
      "traction": 3
    },
    "mmr": 5667,
    "peak_mmr": 6070,
    "rank": 1265,
    "events_played": 69,
    "country": "Ireland",
    "game_stats": {
      "1v1": {
        "events_played": 64,
        "win_rate": "50.0%",
        "win_loss_last_10": "5 - 5",
        "gainloss_last_10": 373,
        "largest_gain": 218,
        "average_score": 82.6,
        "average_score_no_sq": 80.7,
        "average_score_last_10": 91.8,
        "partner_average_score": 82,
        "partner_average_score_no_sq": 85.3
      },
      "2v2": {
        "events_played": 5,
        "win_rate": "60.0%",
        "win_loss_last_10": "3 - 2",
        "gainloss_last_10": -64,
        "largest_gain": 166,
        "average_score": 72,
        "average_score_last_10": 72,
        "partner_average_score": 67.7
      }
    },
    "registry_url": "https://mkcentral.com/registry/players/profile?id=68994"
  },
  {
    "id": "Q-2-92i-4-Tolxlx-6059-0800",
    "name": "Q 2 92i 4 Tolxlx",
    "icon": "Mario",
    "cost": 6541,
    "stats": {
      "speed": 5,
      "acceleration": 7,
      "weight": 6,
      "handling": 2,
      "traction": 7
    },
    "mmr": 5769,
    "peak_mmr": 6059,
    "rank": 1117,
    "events_played": 36,
    "country": "France",
    "game_stats": {
      "1v1": {
        "events_played": 32,
        "win_rate": "56.3%",
        "win_loss_last_10": "5 - 5",
        "gainloss_last_10": 114,
        "largest_gain": 211,
        "average_score": 76.1,
        "average_score_no_sq": 78.8,
        "average_score_last_10": 73.5,
        "partner_average_score": 86.2,
        "partner_average_score_no_sq": 90.5
      },
      "2v2": {
        "events_played": 4,
        "win_rate": "25.0%",
        "win_loss_last_10": "1 - 3",
        "gainloss_last_10": -103,
        "largest_gain": 116,
        "average_score": 60.5,
        "average_score_last_10": 60.5,
        "partner_average_score": 75.5
      }
    },
    "registry_url": "https://mkcentral.com/registry/players/profile?id=59670"
  },
  {
    "id": "tcherriez-4095-9453",
    "name": "tcherriez",
    "icon": "Bowser",
    "cost": 3999,
    "stats": {
      "speed": 9,
      "acceleration": 9,
      "weight": 8,
      "handling": 8,
      "traction": 5
    },
    "mmr": 4139,
    "peak_mmr": 4095,
    "rank": 4043,
    "events_played": 6,
    "country": "United States",
    "game_stats": {
      "1v1": {
        "events_played": 6,
        "win_rate": "33.3%",
        "win_loss_last_10": "2 - 4",
        "gainloss_last_10": -592,
        "largest_gain": 24,
        "average_score": 68.2,
        "average_score_no_sq": 68.2,
        "average_score_last_10": 68.2,
        "partner_average_score": 84,
        "partner_average_score_no_sq": 84
      },
      "2v2": {}
    },
    "registry_url": "https://mkcentral.com/registry/players/profile?id=74840"
  },
  {
    "id": "Heb-4594-1809",
    "name": "Heb",
    "icon": "Bowser",
    "cost": 4610,
    "stats": {
      "speed": 4,
      "acceleration": 4,
      "weight": 2,
      "handling": 6,
      "traction": 7
    },
    "mmr": 4407,
    "peak_mmr": 4594,
    "rank": 3661,
    "events_played": 8,
    "country": "United States",
    "game_stats": {
      "1v1": {
        "events_played": 6,
        "win_rate": "33.3%",
        "win_loss_last_10": "2 - 4",
        "gainloss_last_10": -354,
        "largest_gain": 172,
        "average_score": 76.8,
        "average_score_no_sq": 76.8,
        "average_score_last_10": 76.8
      },
      "2v2": {
        "events_played": 2,
        "win_rate": "50.0%",
        "win_loss_last_10": "1 - 1",
        "gainloss_last_10": 92,
        "largest_gain": 168,
        "average_score": 76,
        "average_score_last_10": 76,
        "partner_average_score": 73.3
      }
    },
    "registry_url": "https://mkcentral.com/registry/players/profile?id=73556"
  }
]